{
  "meta": {
    "version": "2.5.0.15.96516",
    "updateTime": "2026-03-03T00:44:46.846357",
    "totalTactics": 1
  },
  "tactics": [
    {
      "id": "25376a41-1620-473b-a6bf-3d1f5738a99b",
      "name": "PvP 4BG 追猎rush",
      "author": "ZeratalSky",
      "matchup": "pvp",
      "applicableVersion": "2.5.0.15.96516",
      "tacticType": "Timeline",
      "tacVersion": 1,
      "modName": "Scii",
      "modVersion": 100,
      "updateTime": "2026-03-02T00:00:00",
      "filePath": "store/ZeratalSky/4bg_rush.json"
    }
  ]
}